microdrop_plugin_template/__init__.py
microdrop_plugin_template/__init__.py.template
microdrop_plugin_template/create_plugin.py
microdrop_plugin_template/init_hooks.py
microdrop_plugin_template/on_plugin_install.py
microdrop_plugin_template/release.py
microdrop_plugin_template/requirements.txt
microdrop_plugin_template/hooks/Linux/on_plugin_install.sh
microdrop_plugin_template/hooks/Windows/on_plugin_install.bat
microdrop_plugin_template-1.1.post32.dist-info/DESCRIPTION.rst
microdrop_plugin_template-1.1.post32.dist-info/METADATA
microdrop_plugin_template-1.1.post32.dist-info/RECORD
microdrop_plugin_template-1.1.post32.dist-info/WHEEL
microdrop_plugin_template-1.1.post32.dist-info/metadata.json
microdrop_plugin_template-1.1.post32.dist-info/top_level.txt
