Metadata-Version: 2.0
Name: microdrop-plugin-template
Version: 1.1.post32
Summary: Microdrop plugin template
Home-page: https://github.com/wheeler-microfluidics/microdrop-plugin-template
Author: Christian Fobel
Author-email: christian@fobel.net
License: GPL
Platform: UNKNOWN
Requires-Dist: GitPython
Requires-Dist: microdrop-plugin-manager
Requires-Dist: path-helpers
Requires-Dist: pip-helpers (>=0.5.post8)
Requires-Dist: rename-package-files
